hamcall/__init__.py
hamcall/tests/__init__.py
hamcall/tests/test_database.py
hamcall-0.1.5.dist-info/METADATA
hamcall-0.1.5.dist-info/WHEEL
hamcall-0.1.5.dist-info/entry_points.txt
hamcall-0.1.5.dist-info/licenses/LICENSE.txt
hamcall-0.1.5.dist-info/RECORD
