Metadata-Version: 2.4
Name: hamcall
Version: 0.1.5
Summary: A amateur radio callsign lookup database (currently US FCC only)
Project-URL: Homepage, https://github.com/hardaker/hamcall
License: Copyright 2024 Wes Hardaker
License-File: LICENSE.txt
Requires-Python: >=3.10
